kpds_package/__init__.py
kpds_package/config.py
kpds_package/kpds_api.py
kpds_package-1.0.4.2.dist-info/METADATA
kpds_package-1.0.4.2.dist-info/WHEEL
kpds_package-1.0.4.2.dist-info/top_level.txt
kpds_package-1.0.4.2.dist-info/RECORD
